{
    "fluentMethods": true,
    "relationships": [],
    "fields": [
        {
            "fieldName": "amt2Id",
            "fieldType": "Long",
            "fieldValidateRules": [
                "required"
            ]
        },
        {
            "fieldName": "projectId",
            "fieldType": "Long",
            "fieldValidateRules": [
                "required"
            ]
        },
        {
            "fieldName": "shopId",
            "fieldType": "Long",
            "fieldValidateRules": [
                "required"
            ]
        },
        {
            "fieldName": "amt2Info",
            "fieldType": "String",
            "fieldValidateRules": [
                "required"
            ]
        }
    ],
    "changelogDate": "20171228022828",
    "dto": "mapstruct",
    "service": "serviceImpl",
    "entityTableName": "sale_amt2",
    "jpaMetamodelFiltering": false,
    "pagination": "pagination"
}
